LICENSE.txt
README.md
pyproject.toml
setup.cfg
setup.py
path_finder/__init__.py
path_finder/base.py
path_finder/dir_finder.py
path_finder/file_finder.py
path_finder.egg-info/PKG-INFO
path_finder.egg-info/SOURCES.txt
path_finder.egg-info/dependency_links.txt
path_finder.egg-info/not-zip-safe
path_finder.egg-info/requires.txt
path_finder.egg-info/top_level.txt