Metadata-Version: 2.1
Name: path-finder
Version: 1.6
Summary: An interface for finding directories and files
Home-page: https://github.com/hdsr-mid/path_finder
Author: Renier Kramer
Author-email: renier.kramer@hdsr.nl
License: MIT
Download-URL: https://github.com/hdsr-mid/path_finder/archive/v1.6.tar.gz
Keywords: interface,path,directory,filename,glob,regex,find
Platform: UNKNOWN
Classifier: Development Status :: 5 - Production/Stable
Classifier: Intended Audience :: Developers
Classifier: Topic :: Software Development :: Build Tools
Classifier: License :: OSI Approved :: MIT License
Classifier: Programming Language :: Python :: 3
Classifier: Programming Language :: Python :: 3.6
Classifier: Programming Language :: Python :: 3.7
Classifier: Programming Language :: Python :: 3.8
Provides-Extra: test
License-File: LICENSE.txt
